[{"word": "gathering", "total": 9, "occurrences": [{"location": "Book 2, Cant. X., 55.6", "line_text": "Gathering againe, her Host she did renew,"}, {"location": "Book 2, Cant. X., 64.4", "line_text": "Which th'Infants tutors gathering to feare,"}, {"location": "Book 3, Canto I., 23.3", "line_text": "But gathering him round about more neare,"}, {"location": "Book 3, Cant. IIII., 29.8", "line_text": "Gathering sweet daffadillyes, to haue made"}, {"location": "Book 5, Cant. II., 23.8", "line_text": "Whilest he to gathering of the gold did fall."}, {"location": "Book 5, Cant. IIII., 45.6", "line_text": "And gathering them vnto her citties gate,"}], "split_num": 1}, {"word": "gathred", "total": 2, "occurrences": [{"location": "Book 1, Canto I., 25.4", "line_text": "Gathred themselues about her body round,"}, {"location": "Book 3, Cant. IX., 36.8", "line_text": "Gathred the Troian reliques sau'd from flame,"}], "split_num": -1}, {"word": "gaudie", "total": 1, "occurrences": [{"location": "Book 2, Cant. VI., 7.4", "line_text": "With gaudie girlonds, or fresh flowrets dight"}], "split_num": -1}, {"word": "gaue", "total": 92, "occurrences": [{"location": "Book 1, Canto I., 3.2", "line_text": "That greatest Gloriana to him gaue,"}, {"location": "Book 1, Canto I., 11.9", "line_text": "And to the Dwarfe a while his needlesse spere he gaue."}, {"location": "Book 1, Canto I., 38.8", "line_text": "The one of them he gaue a message too,"}, {"location": "Book 1, Cant. II., 13.6", "line_text": "The which her lauish louers to her gaue;"}, {"location": "Book 1, Cant. IIII., 47.9", "line_text": "For that I would not yeeld, that to Sans-foy I gaue."}, {"location": "Book 1, Cant. VII., 16.3", "line_text": "He gaue her gold and purple pall to weare,"}, {"location": "Book 1, Cant. VIII., 29.1", "line_text": "Forthwith he gaue in charge vnto his Squire,"}, {"location": "Book 1, Cant. IX., 18.8", "line_text": "Gaue goodly gifts, the signes of gratefull mynd,"}, {"location": "Book 1, Cant. IX., 19.1", "line_text": "Prince Arthur gaue a boxe of Diamond sure,"}, {"location": "Book 1, Cant. IX., 19.6", "line_text": "Which to requite, the Redcrosse knight him gaue"}, {"location": "Book 1, Cant. IX., 51.3", "line_text": "And gaue it him in hand: his hand did quake,"}, {"location": "Book 1, Cant. X., 20.9", "line_text": "Almightie God her gaue such powre, and puissance great."}, {"location": "Book 1, Cant. X., 22.1", "line_text": "But wise Speranza gaue him comfort sweet,"}, {"location": "Book 1, Cant. X., 34.6", "line_text": "To whom the carefull charge of him she gaue,"}, {"location": "Book 1, Cant. X., 42.7", "line_text": "Whose face he made, all beasts to feare, and gaue"}, {"location": "Book 1, Cant. X., 43.9", "line_text": "He did supply their want, and gaue them euer free."}, {"location": "Book 1, Cant. X., 66.6", "line_text": "Whereof Georgos he thee gaue to name;"}, {"location": "Book 1, Cant. X., 68.5", "line_text": "He thence departing gaue for his paines hyre."}, {"location": "Book 1, Cant. XI., 48.6", "line_text": "Life and long health that gratious ointment gaue,"}, {"location": "Book 1, Cant. XII., 27.3", "line_text": "And sacred pledges he both gaue, and had,"}, {"location": "Book 2, Canto I., 38.3", "line_text": "And after gaue a grone so deepe and low,"}, {"location": "Book 2, Cant. II., 11.2", "line_text": "Vptaking, to the Palmer gaue to beare;"}, {"location": "Book 2, Cant. III., 4.7", "line_text": "Gaue him great ayd, and made him more inclind:"}, {"location": "Book 2, Cant. IIII., 30.8", "line_text": "Of deadly drugs I gaue him drinke anon,"}, {"location": "Book 2, Cant. IIII., 32.1", "line_text": "Feare gaue her wings, and rage enforst my flight;"}, {"location": "Book 2, Cant. V., 22.8", "line_text": "Had kindled: that she gaue into his hond,"}, {"location": "Book 2, Cant. VI., 8.2", "line_text": "Gaue wondrous great contentment to the knight,"}, {"location": "Book 2, Cant. VI., 20.5", "line_text": "Ne gaue him leaue to bid that aged sire"}, {"location": "Book 2, Cant. VI., 38.6", "line_text": "And to that Damzell thankes gaue for reward."}, {"location": "Book 2, Cant. VIII., 20.9", "line_text": "Of hellish Styx, which hidden vertue to it gaue."}, {"location": "Book 2, Cant. VIII., 23.5", "line_text": "Gaue signes of grudge and discontentment vaine:"}, {"location": "Book 2, Cant. VIII., 39.4", "line_text": "Gaue him great hart, and hope of victory."}, {"location": "Book 2, Cant. IX., 14.3", "line_text": "They gaue fresh charge, their forces gan to faile,"}, {"location": "Book 2, Cant. IX., 46.4", "line_text": "Therein gaue light, and flam'd continually:"}, {"location": "Book 2, Cant. X., 41.6", "line_text": "He also gaue to fugitiues of Spayne,"}, {"location": "Book 2, Cant. X., 59.4", "line_text": "And to him gaue for wife his daughter bright,"}, {"location": "Book 2, Cant. X., 61.2", "line_text": "He gaue in wedlocke to Maximian,"}, {"location": "Book 2, Cant. X., 69.8", "line_text": "How much to her we owe, that all vs gaue,"}, {"location": "Book 2, Cant. X., 69.9", "line_text": "That gaue vnto vs all, what euer good we haue."}, {"location": "Book 2, Cant. XI., 36.5", "line_text": "But ground he gaue, and lightly leapt areare:"}, {"location": "Book 2, Cant. XI., 42.9", "line_text": "And gaue against his mother earth a gronefull sownd."}, {"location": "Book 2, Cant. XII., 68.2", "line_text": "That blushing to her laughter gaue more grace,"}, {"location": "Book 3, Canto I., 15.9", "line_text": "And scarse them leasure gaue, her passing to behold."}, {"location": "Book 3, Canto I., 43.9", "line_text": "With which faire Britomart gaue light vnto the day."}, {"location": "Book 3, Canto I., 66.7", "line_text": "And eke the Redcrosse knight gaue her good aid,"}, {"location": "Book 3, Cant. II., 21.2", "line_text": "And gaue vnto king Ryence for his gard,"}, {"location": "Book 3, Cant. IIII., 26.1", "line_text": "For thy she gaue him warning euery day,"}, {"location": "Book 3, Cant. V., 46.8", "line_text": "Thy life she gaue, thy life she doth deserue:"}, {"location": "Book 3, Cant. VI., 17.9", "line_text": "The rest vpon her person gaue attendance great."}, {"location": "Book 3, Cant. VII., 23.1", "line_text": "It forth she cald, and gaue it streight in charge,"}, {"location": "Book 3, Cant. VII., 26.9", "line_text": "Thereto feare gaue her wings, and neede her courage taught."}, {"location": "Book 3, Cant. IX., 34.9", "line_text": "Whom Venus to him gaue for meed of worthinesse."}, {"location": "Book 3, Cant. X., 16.7", "line_text": "Gaue them safe conduct, till to end they came:"}, {"location": "Book 3, Cant. XI., 25.4", "line_text": "Assayld the flame, the which eftsoones gaue place,"}, {"location": "Book 3, Cant. XII., 9.4", "line_text": "And gaue him being, commune to them twaine:"}, {"location": "Book 3, Cant. XII., 43.6", "line_text": "And gaue her leaue at pleasure forth to passe."}, {"location": "Book 4, Cant. III., 18.7", "line_text": "And so gaue way vnto his fell intent:"}, {"location": "Book 4, Cant. III., 46.3", "line_text": "Which straight flew ope, and gaue her way to ride."}, {"location": "Book 4, Cant. V., 3.1", "line_text": "That girdle gaue the vertue of chast loue,"}, {"location": "Book 4, Cant. V., 43.4", "line_text": "Long time resist, gaue place to kindly rest,"}, {"location": "Book 4, Cant. VII., 28.7", "line_text": "But for aduantage ground vnto him gaue,"}, {"location": "Book 4, Cant. XI., 5.9", "line_text": "Which Britomart him gaue, when he did her prouoke."}, {"location": "Book 5, Canto I., 9.2", "line_text": "She gaue vnto him, gotten by her slight"}, {"location": "Book 5, Cant. IIII., 12.7", "line_text": "The portion of that good, which Fortune gaue her,"}, {"location": "Book 5, Cant. IIII., 51.6", "line_text": "And gaue them gifts and things of deare delight."}, {"location": "Book 5, Cant. V., 23.2", "line_text": "And in his hand a distaffe to him gaue,"}, {"location": "Book 5, Cant. VI., 21.4", "line_text": "That gaue none other place. Which when as hee"}, {"location": "Book 5, Cant. VII., 43.4", "line_text": "And gaue to them great liuing and large fee:"}, {"location": "Book 5, Cant. VII., 44.7", "line_text": "Gaue vnto her great comfort and reliefe,"}, {"location": "Book 5, Cant. VIII., 31.2", "line_text": "Vnto his horses gaue his guests for meat,"}, {"location": "Book 5, Cant. VIII., 32.3", "line_text": "Gaue way vnto his horses speedie flying,"}, {"location": "Book 5, Cant. IX., 5.3", "line_text": "Both vnassaylable, gaue him great ayde:"}, {"location": "Book 5, Cant. X., 11.9", "line_text": "Which gaue beginning to her woe and wretchednesse."}, {"location": "Book 5, Cant. X., 13.2", "line_text": "All to his hands, and gaue him soueraine powre"}, {"location": "Book 5, Cant. X., 17.2", "line_text": "Who gaue him roiall giftes and riches rare,"}, {"location": "Book 5, Cant. X., 33.5", "line_text": "Gaue leaue vnto his ghost from thraldome bound,"}, {"location": "Book 5, Cant. X., 35.3", "line_text": "Ne to their force gaue way, that was great wonder,"}, {"location": "Book 5, Cant. XI., 46.5", "line_text": "Albe that it most safety to him gaue,"}, {"location": "Book 5, Cant. XI., 53.3", "line_text": "Who when he gaue me armes, in field to fight,"}, {"location": "Book 5, Cant. XI., 53.4", "line_text": "Gaue me a shield, in which he did endosse"}, {"location": "Book 5, Cant. XII., 9.8", "line_text": "The morrow next, ne gaue him longer day;"}, {"location": "Book 6, Canto I., 46.7", "line_text": "She freely gaue that Castle for his paine,"}, {"location": "Book 6, Canto I., 47.3", "line_text": "But gaue them streight vnto that Squire againe,"}, {"location": "Book 6, Cant. VII., 34.8", "line_text": "Gaue euidence, that they were all betrayd,"}, {"location": "Book 6, Cant. VIII., 9.6", "line_text": "And gaue his foe good hope of victory."}, {"location": "Book 6, Cant. VIII., 14.3", "line_text": "That way to them he gaue forth right to pas."}, {"location": "Book 6, Cant. VIII., 38.4", "line_text": "Then when she wakt, they all gaue one consent,"}, {"location": "Book 6, Cant. IX., 7.3", "line_text": "They prayd him sit, and gaue him for to feed"}, {"location": "Book 6, Cant. IX., 44.9", "line_text": "Gaue it to Coridon, and said he wonne it well."}, {"location": "Book 6, Cant. XI., 7.3", "line_text": "Which gaue him hope, and did him halfe perswade,"}, {"location": "Book 6, Cant. XI., 38.9", "line_text": "But gently waking them, gaue them the time of day."}, {"location": "Book 6, Cant. XII., 17.6", "line_text": "Whilest ye in durance dwelt, ye to me gaue"}], "split_num": -1}, {"word": "gauest", "total": 1, "occurrences": [{"location": "Book 5, Cant. VII., 32.6", "line_text": "And tell him for his sake thy life thou gauest."}], "split_num": -1}, {"word": "gauld", "total": 1, "occurrences": [{"location": "Book 4, Cant. V., 31.8", "line_text": "The more it gauld, and grieu'd him night and day,"}], "split_num": -1}, {"word": "gauntlet", "total": 1, "occurrences": [{"location": "Book 1, Cant. IIII., 43.1", "line_text": "But threw his gauntlet as a sacred pledge,"}], "split_num": -1}, {"word": "gay", "total": 35, "occurrences": [{"location": "Book 1, Cant. II., 12.7", "line_text": "In whose great shield was writ with letters gay"}, {"location": "Book 1, Cant. IIII., 14.9", "line_text": "Their gay attire: each others greater pride does spight."}, {"location": "Book 1, Cant. IIII., 17.2", "line_text": "Adorned all with gold, and girlonds gay,"}, {"location": "Book 1, Cant. V., 16.5", "line_text": "Greatly aduauncing his gay cheualree."}, {"location": "Book 1, Cant. VIII., 3.7", "line_text": "And tassels gay. Wyde wonders ouer all"}, {"location": "Book 1, Cant. VIII., 16.7", "line_text": "That her gay garments staynd with filthy gore,"}, {"location": "Book 1, Cant. X., 39.2", "line_text": "In which were not rich tyres, nor garments gay,"}, {"location": "Book 1, Cant. XI., 34.5", "line_text": "And deckt himselfe with feathers youthly gay,"}, {"location": "Book 2, Canto I., 49.9", "line_text": "Gay steed with spurs did pricke, the good Sir Mortdant was."}, {"location": "Book 2, Cant. II., 19.1", "line_text": "These two gay knights, vowd to so diuerse loues,"}, {"location": "Book 2, Cant. III., 5.7", "line_text": "But for in court gay portaunce he perceiu'd,"}, {"location": "Book 2, Cant. III., 29.2", "line_text": "And at her backe a bow and quiuer gay,"}, {"location": "Book 2, Cant. III., 36.4", "line_text": "She her gay painted plumes disorderid,"}, {"location": "Book 2, Cant. IIII., 45.6", "line_text": "Great glory and gay spoile sure hast thou got,"}, {"location": "Book 2, Cant. V., 32.4", "line_text": "Amidst a flocke of Damzels fresh and gay,"}, {"location": "Book 2, Cant. VI., 11.6", "line_text": "And that gay paire issuing on the shore"}, {"location": "Book 2, Cant. VII., 10.8", "line_text": "Faire shields, gay steedes, bright armes be my delight:"}, {"location": "Book 2, Cant. VII., 44.6", "line_text": "And thereon sat a woman gorgeous gay,"}, {"location": "Book 2, Cant. XI., 17.8", "line_text": "With his gay Squire issuing did espy,"}, {"location": "Book 3, Canto I., 56.8", "line_text": "Gan choose his dame with Basciomani gay,"}, {"location": "Book 3, Cant. IIII., 29.9", "line_text": "Gay girlonds, from the Sun their forheads faire to shade."}, {"location": "Book 3, Cant. VI., 21.4", "line_text": "Of your gay sonne, that giues ye so good ayd"}, {"location": "Book 3, Cant. VI., 41.9", "line_text": "Their goodly meriment, and gay felicitie."}, {"location": "Book 3, Cant. VIII., 9.1", "line_text": "Him shaped thus, she deckt in garments gay,"}, {"location": "Book 3, Cant. VIII., 26.9", "line_text": "Her garments gay with scales of fish, that all did fill."}, {"location": "Book 3, Cant. IX., 20.4", "line_text": "Her golden locks, that were in tramels gay"}, {"location": "Book 4, Cant. II., 29.7", "line_text": "How euer gay and goodly be the style,"}, {"location": "Book 4, Cant. X., 37.6", "line_text": "All deckt with crownes, & chaynes, and girlands gay,"}, {"location": "Book 5, Canto I., 14.5", "line_text": "That her gay clothes did in discolour die."}, {"location": "Book 5, Cant. II., 40.4", "line_text": "How euer gay their blossome or their blade"}, {"location": "Book 5, Cant. XII., 13.6", "line_text": "Dispreds the glorie of her leaues gay;"}, {"location": "Book 6, Proem, 5.6", "line_text": "Yet is that glasse so gay, that it can blynd"}, {"location": "Book 6, Cant. V., 38.5", "line_text": "Deckt with greene boughes, and flowers gay beseene."}, {"location": "Book 6, Cant. IX., 22.1", "line_text": "To them, that list, the worlds gay showes I leaue,"}, {"location": "Book 6, Cant. IX., 27.4", "line_text": "That all this worlds gay showes, which we admire,"}], "split_num": -1}, {"word": "gaynd", "total": 3, "occurrences": [{"location": "Book 2, Cant. V., 15.5", "line_text": "Yet shortly gaynd, that losse exceeded farre:"}, {"location": "Book 2, Cant. V., 31.5", "line_text": "Gaynd in Nemea goodly victoree;"}, {"location": "Book 2, Cant. X., 45.9", "line_text": "Till aged Hely by dew heritage it gaynd."}], "split_num": -1}, {"word": "gayne", "total": 4, "occurrences": [{"location": "Book 1, Cant. VII., 15.2", "line_text": "To gayne so goodly guerdon, as she spake:"}, {"location": "Book 2, Cant. II., 45.5", "line_text": "Ill by ensample good doth often gayne."}, {"location": "Book 4, Cant. IX., 4.5", "line_text": "That enterprize, for greatest glories gayne."}, {"location": "Book 6, Cant. III., 32.2", "line_text": "So fare on foote till thou another gayne,"}], "split_num": -1}, {"word": "gayned", "total": 7, "occurrences": [{"location": "Book 5, Cant. III., 35.6", "line_text": "Hence fare on foot, till he an horse haue gayned."}, {"location": "Book 5, Cant. V., 17.9", "line_text": "No fayrer conquest, then that with goodwill is gayned."}, {"location": "Book 5, Cant. V., 44.4", "line_text": "For feare her mistresse shold haue knowledge gayned,"}, {"location": "Book 5, Cant. V., 54.3", "line_text": "Vnto her Queene, his freedome to haue gayned;"}, {"location": "Book 5, Cant. V., 57.8", "line_text": "Vntill his owne true loue his freedome gayned,"}, {"location": "Book 5, Cant. XII., 32.9", "line_text": "As she had got thereby, and gayned a great stake."}, {"location": "Book 6, Canto I., 3.4", "line_text": "The which in all mens liking gayned place,"}], "split_num": -1}, {"word": "gaynes", "total": 1, "occurrences": [{"location": "Book 1, Cant. VI., 3.8", "line_text": "For greater conquest of hard loue he gaynes,"}], "split_num": -1}, {"word": "gaynest", "total": 1, "occurrences": [{"location": "Book 2, Cant. VII., 13.9", "line_text": "So mak'st thou kings, & gaynest wrongfull gouernement."}], "split_num": -1}, {"word": "gayns", "total": 1, "occurrences": [{"location": "Book 1, Cant. XI., argument.3", "line_text": "The third him ouerthrowes, and gayns"}], "split_num": -1}, {"word": "gaynst", "total": 1, "occurrences": [{"location": "Book 6, Cant. II., 18.9", "line_text": "In which he had good right gaynst all, that it gainesayd."}], "split_num": -1}, {"word": "gazd", "total": 4, "occurrences": [{"location": "Book 1, Canto I., 26.3", "line_text": "Deuoure their dam; on whom while so he gazd,"}, {"location": "Book 1, Cant. XII., 9.5", "line_text": "And gazd vpon with gaping wonderment."}, {"location": "Book 2, Cant. VIII., 9.4", "line_text": "Gaz'd after him, as fowle escapt by flight;"}, {"location": "Book 6, Cant. VII., 42.8", "line_text": "He gaz'd about, and stared horriblie,"}], "split_num": -1}, {"word": "gaze", "total": 13, "occurrences": [{"location": "Book 1, Cant. IIII., 16.8", "line_text": "Do ride each other, vpon her to gaze:"}, {"location": "Book 1, Cant. V., 32.9", "line_text": "To gaze on earthly wight, that with the Night durst ride."}, {"location": "Book 1, Cant. V., 36.3", "line_text": "To gaze on them; who forth by them doe pace,"}, {"location": "Book 1, Cant. VII., 22.4", "line_text": "Or liking find to gaze on earthly mould,"}, {"location": "Book 2, Cant. II., 5.1", "line_text": "Whom thus at gaze, the Palmer gan to bord"}, {"location": "Book 3, Cant. VII., 7.6", "line_text": "And with fell looke and hollow deadly gaze"}, {"location": "Book 4, Cant. II., 17.3", "line_text": "And round about themselues a while did gaze,"}, {"location": "Book 4, Cant. IIII., 14.6", "line_text": "That men on him the more might gaze alone."}, {"location": "Book 4, Cant. X., 24.6", "line_text": "Low looking dales, disloignd from common gaze;"}, {"location": "Book 5, Cant. VII., 5.9", "line_text": "But thought, that she thereon could neuer gaze her fill."}, {"location": "Book 5, Cant. IX., 24.1", "line_text": "They ceast their clamors vpon them to gaze;"}, {"location": "Book 6, Cant. X., 4.1", "line_text": "For what hath all that goodly glorious gaze"}, {"location": "Book 6, Cant. XI., 13.8", "line_text": "Awhile on her they greedily did gaze,"}], "split_num": -1}, {"word": "gazed", "total": 6, "occurrences": [{"location": "Book 3, Canto I., 17.1", "line_text": "So as they gazed after her a while,"}, {"location": "Book 3, Cant. VII., 13.6", "line_text": "So inly smot, that as one, which had gazed"}, {"location": "Book 3, Cant. XI., 49.8", "line_text": "But euermore and more vpon it gazed,"}, {"location": "Book 4, Cant. II., 20.9", "line_text": "But gazed on their harmes, not pittying their estate."}, {"location": "Book 5, Cant. III., 18.7", "line_text": "He gazed still vpon that snowy mayd;"}, {"location": "Book 6, Cant. VIII., 26.6", "line_text": "Downe on his golden feete he often gazed,"}], "split_num": -1}, {"word": "gazefull", "total": 1, "occurrences": [{"location": "Book 4, Cant. X., 28.2", "line_text": "Nor happie howre, beheld with gazefull eye,"}], "split_num": -1}, {"word": "gazement", "total": 1, "occurrences": [{"location": "Book 5, Cant. III., 17.3", "line_text": "Couered from peoples gazement with a vele."}], "split_num": -1}, {"word": "gazer", "total": 1, "occurrences": [{"location": "Book 5, Cant. VIII., 38.1", "line_text": "Like lightening flash, that hath the gazer burned,"}], "split_num": -1}, {"word": "gazers", "total": 3, "occurrences": [{"location": "Book 1, Cant. V., 9.7", "line_text": "Great ruth in all the gazers harts did grow,"}, {"location": "Book 2, Cant. III., 22.8", "line_text": "And gazers sense with double pleasure fed,"}, {"location": "Book 4, Cant. X., 49.8", "line_text": "Ne rov'd at randon after gazers guyse,"}], "split_num": -1}, {"word": "gazing", "total": 23, "occurrences": [{"location": "Book 1, Cant. III., 8.4", "line_text": "The kingly beast vpon her gazing stood;"}, {"location": "Book 1, Cant. IIII., 7.1", "line_text": "By them they passe, all gazing on them round,"}, {"location": "Book 1, Cant. IIII., 17.6", "line_text": "The Gods stand gazing on, when she does ride"}, {"location": "Book 1, Cant. V., 3.2", "line_text": "Where earely waite him many a gazing eye,"}, {"location": "Book 1, Cant. VI., 16.4", "line_text": "To thinke of wight so faire, but gazing stood,"}, {"location": "Book 1, Cant. VII., 35.9", "line_text": "He would them gazing blind, or turne to other hew."}, {"location": "Book 1, Cant. X., 56.1", "line_text": "As he thereon stood gazing, he might see"}, {"location": "Book 2, Cant. IX., 33.3", "line_text": "And gazing wonder they their minds did fill;"}, {"location": "Book 2, Cant. XII., 66.2", "line_text": "Gazing a while at his vnwonted guise;"}, {"location": "Book 2, Cant. XII., 69.1", "line_text": "On which when gazing him the Palmer saw,"}, {"location": "Book 3, Cant. VI., 27.6", "line_text": "And gazing each on other, nought bespake:"}, {"location": "Book 3, Cant. IX., 23.4", "line_text": "Stood gazing, as if suddein great affright"}, {"location": "Book 3, Cant. XI., 53.4", "line_text": "Her greedy eyes with gazing a long space:"}, {"location": "Book 3, Cant. XII., 29.2", "line_text": "And gazing on that Chambers ornament,"}, {"location": "Book 4, Cant. III., 37.4", "line_text": "Stood gazing, filled were with rufull tine,"}, {"location": "Book 4, Cant. V., 26.3", "line_text": "All on her gazing wisht, and vowd, and prayd,"}, {"location": "Book 4, Cant. VI., 22.1", "line_text": "And he himselfe long gazing thereupon,"}, {"location": "Book 4, Cant. VII., 32.6", "line_text": "Yet ouer him she there long gazing stood,"}, {"location": "Book 4, Cant. IX., 11.8", "line_text": "Thus gazing long, at them much wondred he,"}, {"location": "Book 5, Cant. VII., 5.8", "line_text": "And thereuppon long while stood gazing still,"}, {"location": "Book 5, Cant. XI., 15.6", "line_text": "Which there stood gazing from the Citties wall"}, {"location": "Book 6, Cant. IX., 11.9", "line_text": "Caught like the bird, which gazing still on others stands."}, {"location": "Book 6, Cant. IX., 12.1", "line_text": "So stood he still long gazing thereupon,"}], "split_num": -1}, {"word": "gealosie", "total": 10, "occurrences": [{"location": "Book 2, Cant. IIII., 35.1", "line_text": "Wrath, gealosie, griefe, loue do thus expell:"}, {"location": "Book 2, Cant. IIII., 35.2", "line_text": "Wrath is a fire, and gealosie a weede,"}, {"location": "Book 2, Cant. IIII., 35.9", "line_text": "So shall wrath, gealosie, griefe, loue dye and decay."}, {"location": "Book 2, Cant. VII., 22.4", "line_text": "But gnawing Gealosie out of their sight"}, {"location": "Book 3, Cant. VI., 41.6", "line_text": "Without fell rancor, or fond gealosie;"}, {"location": "Book 3, Cant. IX., argument.2", "line_text": "For peeuish gealosie:"}, {"location": "Book 3, Cant. X., 48.6", "line_text": "That all his hart with gealosie did swell;"}, {"location": "Book 3, Cant. X., 55.5", "line_text": "Griefe, and despight, and gealosie, and scorne"}, {"location": "Book 3, Cant. X., 60.9", "line_text": "Forgot he was a man, and Gealosie is hight."}, {"location": "Book 3, Cant. XI., 1.5", "line_text": "Fowle Gealosie, that turnest loue diuine"}], "split_num": -1}, {"word": "gealosy", "total": 3, "occurrences": [{"location": "Book 1, Cant. XII., 41.3", "line_text": "Ne wicked enuie, ne vile gealosy"}, {"location": "Book 3, Canto I., 18.2", "line_text": "Full of great enuie and fell gealosy,"}, {"location": "Book 3, Cant. X., 22.5", "line_text": "That is the father of fowle gealosy,"}], "split_num": -1}, {"word": "gealosye", "total": 2, "occurrences": [{"location": "Book 3, Cant. X., 17.4", "line_text": "Into huge waues of griefe and gealosye"}, {"location": "Book 4, Cant. X., 28.5", "line_text": "That being free from feare and gealosye,"}], "split_num": -1}, {"word": "gealous", "total": 16, "occurrences": [{"location": "Book 1, Cant. II., 5.6", "line_text": "Which when he saw, he burnt with gealous fire,"}, {"location": "Book 1, Cant. II., 12.3", "line_text": "Still flying from his thoughts and gealous feare;"}, {"location": "Book 1, Cant. V., 37.9", "line_text": "And with her gealous termes his open eares abused."}, {"location": "Book 2, Cant. IIII., 18.7", "line_text": "In which we long time without gealous feares,"}, {"location": "Book 2, Cant. IIII., 28.9", "line_text": "Then wound of gealous worme, and shame of such repriefe."}, {"location": "Book 3, Cant. IX., 4.9", "line_text": "And to be free from hard restraint and gealous feares."}, {"location": "Book 3, Cant. IX., 28.9", "line_text": "Empoisned was with priuy lust, and gealous dred."}, {"location": "Book 3, Cant. XI., 33.2", "line_text": "Deceiu'd of gealous Iuno, did require"}, {"location": "Book 4, Cant. V., 30.8", "line_text": "That stryfull hag with gealous discontent"}, {"location": "Book 4, Cant. V., 31.3", "line_text": "The which like thornes did pricke his gealous hart,"}, {"location": "Book 4, Cant. V., 45.9", "line_text": "And ghesse the man to be dismayd with gealous dread."}, {"location": "Book 4, Cant. VI., 7.5", "line_text": "For fell despight, and gnaw his gealous hart,"}, {"location": "Book 4, Cant. VI., 28.2", "line_text": "That all his gealous feare he false had found,"}, {"location": "Book 6, Cant. II., 16.6", "line_text": "Of their franke loues, free from all gealous spyes:"}, {"location": "Book 6, Cant. II., 29.5", "line_text": "Whose gealous dread induring not a peare,"}, {"location": "Book 6, Cant. IX., 38.4", "line_text": "And many gealous thoughts conceiu'd in vaine,"}], "split_num": -1}, {"word": "gealousie", "total": 1, "occurrences": [{"location": "Book 6, Cant. IX., 39.3", "line_text": "And byte his lip, and euen for gealousie"}], "split_num": -1}, {"word": "geant", "total": 1, "occurrences": [{"location": "Book 1, Cant. VII., 8.4", "line_text": "An hideous Geant horrible and hye,"}], "split_num": -1}, {"word": "geants", "total": 1, "occurrences": [{"location": "Book 1, Cant. VIII., 5.1", "line_text": "The same before the Geants gate he blew,"}], "split_num": -1}, {"word": "geare", "total": 7, "occurrences": [{"location": "Book 2, Cant. IIII., 26.8", "line_text": "Aray thy selfe in her most gorgeous geare,"}, {"location": "Book 2, Cant. VI., 21.7", "line_text": "But when he saw her toy, and gibe, and geare,"}, {"location": "Book 4, Cant. XI., 45.2", "line_text": "Clad in a vesture of vnknowen geare,"}, {"location": "Book 5, Cant. VIII., 30.1", "line_text": "Thus goe they both together to their geare,"}, {"location": "Book 5, Cant. XI., 10.2", "line_text": "Ere he were throughly buckled to his geare;"}, {"location": "Book 6, Cant. III., 6.5", "line_text": "That to Sir Calidore was easie geare;"}, {"location": "Book 6, Cant. VIII., 16.7", "line_text": "So huge a burden on such broken geare,"}], "split_num": -1}, {"word": "geares", "total": 1, "occurrences": [{"location": "Book 5, Cant. II., 50.4", "line_text": "And spoyling all her geares and goodly ray,"}], "split_num": -1}, {"word": "geason", "total": 1, "occurrences": [{"location": "Book 6, Cant. IIII., 37.2", "line_text": "Found nothing that he said, vnmeet nor geason,"}], "split_num": -1}, {"word": "geaunt", "total": 3, "occurrences": [{"location": "Book 1, Cant. VII., 12.1", "line_text": "The Geaunt strooke so maynly mercilesse,"}, {"location": "Book 1, Cant. VII., 14.1", "line_text": "So daunted when the Geaunt saw the knight,"}, {"location": "Book 3, Cant. XI., 3.4", "line_text": "From an huge Geaunt, that with hideous"}], "split_num": -1}, {"word": "geauntesse", "total": 4, "occurrences": [{"location": "Book 3, Cant. VII., 39.7", "line_text": "So ran the Geauntesse vnto the fight;"}, {"location": "Book 3, Cant. VII., 47.2", "line_text": "That Geauntesse Argante is behight,"}, {"location": "Book 3, Cant. VII., 52.2", "line_text": "That Geauntesse, is not such, as she seemed,"}, {"location": "Book 4, Cant. VIII., 47.2", "line_text": "Of an huge Geauntesse whylome was bred;"}], "split_num": -1}, {"word": "geaunts", "total": 1, "occurrences": [{"location": "Book 3, Cant. IX., 49.8", "line_text": "Saue an huge nation of the Geaunts broode,"}], "split_num": -1}, {"word": "gehons", "total": 1, "occurrences": [{"location": "Book 1, Cant. VII., 43.9", "line_text": "And Gehons golden waues doe wash continually."}], "split_num": -1}, {"word": "gelly", "total": 1, "occurrences": [{"location": "Book 3, Cant. IIII., 40.6", "line_text": "They softly wipt away the gelly blood"}], "split_num": -1}, {"word": "gelosie", "total": 1, "occurrences": [{"location": "Book 2, Cant. IIII., 34.9", "line_text": "Wrath, gelosie, griefe, loue this Squire haue layd thus low."}], "split_num": -1}, {"word": "gelosy", "total": 2, "occurrences": [{"location": "Book 1, Cant. IIII., 24.3", "line_text": "And whally eyes (the signe of gelosy,)"}, {"location": "Book 2, Cant. IIII., 23.1", "line_text": "The gnawing anguish and sharpe gelosy,"}], "split_num": -1}, {"word": "gelt", "total": 1, "occurrences": [{"location": "Book 4, Cant. VII., 21.3", "line_text": "But like a ghastly Gelt, whose wits are reaued,"}], "split_num": -1}, {"word": "gemme", "total": 1, "occurrences": [{"location": "Book 6, Cant. X., 12.7", "line_text": "Another Damzell, as a precious gemme,"}], "split_num": -1}, {"word": "gemmes", "total": 2, "occurrences": [{"location": "Book 1, Cant. X., 31.6", "line_text": "Adornd with gemmes and owches wondrous faire,"}, {"location": "Book 5, Cant. IX., 27.6", "line_text": "Adorned all with gemmes of endlesse price,"}], "split_num": -1}, {"word": "gems", "total": 1, "occurrences": [{"location": "Book 5, Cant. VII., 13.9", "line_text": "Her selfe, adorn'd with gems and iewels manifold."}], "split_num": -1}, {"word": "genealogie", "total": 1, "occurrences": [{"location": "Book 3, Cant. IX., 33.7", "line_text": "And fetch from heauen thy great Genealogie,"}], "split_num": -1}, {"word": "generall", "total": 1, "occurrences": [{"location": "Book 6, Cant. XI., 31.5", "line_text": "Were by them slaine by generall consent;"}], "split_num": -1}, {"word": "generation", "total": 4, "occurrences": [{"location": "Book 2, Cant. XII., 47.3", "line_text": "Of life, and generation of all"}, {"location": "Book 3, Cant. VI., 9.1", "line_text": "Great father he of generation"}, {"location": "Book 4, Cant. X., 46.9", "line_text": "In generation seeke to quench their inward fire."}, {"location": "Book 4, Cant. XII., 1.8", "line_text": "So fertile be the flouds in generation,"}], "split_num": -1}, {"word": "generous", "total": 2, "occurrences": [{"location": "Book 3, Cant. III., 57.4", "line_text": "And generous stout courage did inspire,"}, {"location": "Book 4, Cant. III., 14.5", "line_text": "Through secret feeling of his generous spright,"}], "split_num": -1}, {"word": "genius", "total": 3, "occurrences": [{"location": "Book 2, Cant. XII., 47.1", "line_text": "They in that place him Genius did call:"}, {"location": "Book 3, Cant. VI., 31.8", "line_text": "Old Genius the porter of them was,"}, {"location": "Book 3, Cant. VI., 31.9", "line_text": "Old Genius, the which a double nature has."}], "split_num": -1}, {"word": "gent", "total": 14, "occurrences": [{"location": "Book 1, Cant. IX., 6.1", "line_text": "Well worthy impe, said then the Lady gent,"}, {"location": "Book 1, Cant. IX., 27.6", "line_text": "He lou'd, as was his lot, a Ladie gent,"}, {"location": "Book 2, Canto I., 30.6", "line_text": "A knight had wrought against a Ladie gent;"}, {"location": "Book 2, Cant. X., 52.8", "line_text": "Forwasted all, till Genuissa gent"}, {"location": "Book 2, Cant. XI., 17.5", "line_text": "Faire mote he thee, the prowest and most gent,"}, {"location": "Book 3, Canto I., 44.4", "line_text": "For they all seemed curteous and gent,"}, {"location": "Book 3, Canto I., 67.6", "line_text": "Was vsd of Knights and Ladies seeming gent:"}, {"location": "Book 3, Cant. IIII., 45.4", "line_text": "Of courteous knights, the Prince, and Faery gent,"}, {"location": "Book 3, Cant. IIII., 49.6", "line_text": "Hauing farre off espyde a Tassell gent,"}, {"location": "Book 3, Cant. V., 10.5", "line_text": "Therefore, faire Sir, for loue of knighthood gent,"}, {"location": "Book 3, Cant. VII., 3.8", "line_text": "Ne foot could further moue: the Lady gent"}, {"location": "Book 3, Cant. XI., 46.1", "line_text": "Kings Queenes, Lords Ladies, Knights & Damzels gent"}, {"location": "Book 5, Cant. X., 14.9", "line_text": "In th'hearing of full many Knights and Ladies gent."}, {"location": "Book 6, Cant. II., 16.4", "line_text": "Within a wood, whereas a Ladie gent"}], "split_num": -1}, {"word": "gentility", "total": 1, "occurrences": [{"location": "Book 3, Cant. VI., 1.8", "line_text": "All ciuill vsage and gentility,"}], "split_num": -1}, {"word": "gentle", "total": 214, "occurrences": [{"location": "Book 1, Proem, 1.5", "line_text": "And sing of Knights and Ladies gentle deeds;"}, {"location": "Book 1, Proem, 3.8", "line_text": "In loues and gentle iollities arrayd,"}, {"location": "Book 1, Canto I., 1.1", "line_text": "A Gentle Knight was pricking on the plaine,"}, {"location": "Book 1, Canto I., 23.1", "line_text": "As gentle Shepheard in sweete euen-tide,"}, {"location": "Book 1, Canto I., 40.6", "line_text": "Who oft is wont to trouble gentle Sleepe."}, {"location": "Book 1, Canto I., 49.8", "line_text": "With gentle blandishment and louely looke,"}, {"location": "Book 1, Canto I., 50.8", "line_text": "Tho can she weepe, to stirre vp gentle ruth,"}, {"location": "Book 1, Canto I., 55.2", "line_text": "Much grieu'd to thinke that gentle Dame so light,"}, {"location": "Book 1, Cant. II., 8.8", "line_text": "Did search, sore grieued in her gentle brest,"}, {"location": "Book 1, Cant. II., 30.5", "line_text": "Which to expresse, he bends his gentle wit,"}, {"location": "Book 1, Cant. II., 35.4", "line_text": "To loue this gentle Lady, whom ye see,"}, {"location": "Book 1, Cant. III., 34.1", "line_text": "When nigh he drew vnto this gentle payre"}, {"location": "Book 1, Cant. IIII., 13.3", "line_text": "A gentle Husher, Vanitie by name"}, {"location": "Book 1, Cant. IIII., 46.1", "line_text": "With gentle wordes he can her fairely greet,"}, {"location": "Book 1, Cant. VI., 17.6", "line_text": "A gentle Hynd, the which the louely boy"}, {"location": "Book 1, Cant. VI., 19.5", "line_text": "During which time her gentle wit she plyes,"}, {"location": "Book 1, Cant. VI., 31.7", "line_text": "On gentle Dame, so hurtlesse, and so trew:"}, {"location": "Book 1, Cant. VI., 33.3", "line_text": "The gentle virgin left behind alone"}, {"location": "Book 1, Cant. VII., 6.1", "line_text": "Hereof this gentle knight vnweeting was,"}, {"location": "Book 1, Cant. VII., 37.1", "line_text": "A gentle youth, his dearely loued Squire"}, {"location": "Book 1, Cant. VII., 40.1", "line_text": "Ah Ladie deare, quoth then the gentle knight,"}, {"location": "Book 1, Cant. VIII., 39.4", "line_text": "For ruth of gentle knight so fowle forlore:"}, {"location": "Book 1, Cant. IX., 3.9", "line_text": "To be vpbrought in gentle thewes and martiall might."}, {"location": "Book 1, Cant. IX., 4.8", "line_text": "His tombling billowes rolls with gentle rore:"}, {"location": "Book 1, Cant. IX., 16.5", "line_text": "Till gentle Vna thus to him gan say;"}, {"location": "Book 1, Cant. IX., 17.1", "line_text": "Thine, O then, said the gentle Redcrosse knight,"}, {"location": "Book 1, Cant. IX., 24.7", "line_text": "The gentle knight; who nought to him replide,"}, {"location": "Book 1, Cant. IX., 37.3", "line_text": "When as the gentle Redcrosse knight did vew,"}, {"location": "Book 1, Cant. X., 7.1", "line_text": "There fairely them receiues a gentle Squire,"}, {"location": "Book 1, Cant. X., 31.8", "line_text": "And by her side there sate a gentle paire"}, {"location": "Book 1, Cant. XI., 33.5", "line_text": "Vp rose the gentle virgin from her place,"}, {"location": "Book 1, Cant. XI., 50.1", "line_text": "When gentle Vna saw the second fall"}, {"location": "Book 1, Cant. XII., 16.7", "line_text": "For neuer gentle knight, as he of late,"}, {"location": "Book 1, Cant. XII., 33.8", "line_text": "This gentle knight into so great distresse,"}, {"location": "Book 2, Canto I., 13.5", "line_text": "Where sate a gentle Lady all alone,"}, {"location": "Book 2, Canto I., 17.1", "line_text": "Eftsoone she said, Ah gentle trustie Squire,"}, {"location": "Book 2, Canto I., 17.8", "line_text": "A gentle Ladie, or her wrong through might:"}, {"location": "Book 2, Canto I., 19.3", "line_text": "Or euer gentle Damzell so abuse:"}, {"location": "Book 2, Canto I., 33.9", "line_text": "For well ye worthie bene for worth and gentle thewes."}, {"location": "Book 2, Canto I., 38.6", "line_text": "As gentle Hynd, whose sides with cruell steele"}, {"location": "Book 2, Canto I., 46.1", "line_text": "The gentle knight her soone with carefull paine"}, {"location": "Book 2, Cant. III., 2.5", "line_text": "And all that gentle noriture ensu'th:"}, {"location": "Book 2, Cant. III., 10.6", "line_text": "To thinke without desert of gentle deed,"}, {"location": "Book 2, Cant. IIII., 1.8", "line_text": "Proper to gentle bloud; some others faine"}, {"location": "Book 2, Cant. IIII., 20.9", "line_text": "O wretched man, that would abuse so gentle Dame."}, {"location": "Book 2, Cant. V., 30.2", "line_text": "A gentle streame, whose murmuring waue did play"}, {"location": "Book 2, Cant. VI., 26.5", "line_text": "That gentle Ladie did to him impart,"}, {"location": "Book 2, Cant. VI., 35.3", "line_text": "But louely peace, and gentle amitie,"}, {"location": "Book 2, Cant. VI., 36.6", "line_text": "Of courteous clemencie in gentle hart."}, {"location": "Book 2, Cant. VII., 15.9", "line_text": "And with vncomely weedes the gentle waue accloyes."}, {"location": "Book 2, Cant. VII., 50.1", "line_text": "Gramercy Mammon (said the gentle knight)"}, {"location": "Book 2, Cant. VIII., 29.6", "line_text": "So streightly God doth iudge. But gentle knight,"}, {"location": "Book 2, Cant. IX., 2.5", "line_text": "Till him the Prince with gentle court did bord;"}, {"location": "Book 2, Cant. IX., 18.3", "line_text": "Yet was she woo'd of many a gentle knight,"}, {"location": "Book 2, Cant. IX., 20.3", "line_text": "Where gentle court and gracious delight"}, {"location": "Book 2, Cant. IX., 36.9", "line_text": "As if some pensiue thought co[n]straind her gentle spright."}, {"location": "Book 2, Cant. IX., 37.5", "line_text": "Gentle Madame, why beene ye thus dismaid,"}, {"location": "Book 2, Cant. IX., 40.2", "line_text": "Another Damsell of that gentle crew,"}, {"location": "Book 2, Cant. X., 9.2", "line_text": "Polluted this same gentle soyle long time:"}, {"location": "Book 2, Cant. X., 77.5", "line_text": "Till gentle Alma seeing it so late,"}, {"location": "Book 2, Cant. XI., 29.8", "line_text": "Had not his gentle Squire beheld his paine,"}, {"location": "Book 2, Cant. XII., 32.3", "line_text": "O thou faire sonne of gentle Faery,"}, {"location": "Book 2, Cant. XII., 71.9", "line_text": "The gentle warbling wind low answered to all."}, {"location": "Book 3, Canto I., 18.1", "line_text": "Which outrage when those gentle knights did see,"}, {"location": "Book 3, Canto I., 31.6", "line_text": "Faire Ladies, and of many a gentle knight,"}, {"location": "Book 3, Canto I., 49.9", "line_text": "And in each gentle hart desire of honour breeds."}, {"location": "Book 3, Canto I., 55.4", "line_text": "Or rudely sdeigne a gentle harts request;"}, {"location": "Book 3, Canto I., 56.7", "line_text": "And euery knight, and euery gentle Squire"}, {"location": "Book 3, Cant. II., 9.6", "line_text": "A gentle knight with so vnknightly blame:"}, {"location": "Book 3, Cant. II., 12.6", "line_text": "It ill beseemes a knight of gentle sort,"}, {"location": "Book 3, Cant. II., 15.7", "line_text": "Such secret ease felt gentle Britomart,"}, {"location": "Book 3, Cant. II., 24.5", "line_text": "And friends to termes of gentle truce entize,"}, {"location": "Book 3, Cant. II., 51.7", "line_text": "But loue, that is in gentle brest begonne,"}, {"location": "Book 3, Cant. IIII., 10.3", "line_text": "At last blow vp some gentle gale of ease,"}, {"location": "Book 3, Cant. IIII., 47.1", "line_text": "But Timias, the Princes gentle Squire,"}, {"location": "Book 3, Cant. IIII., 49.3", "line_text": "Was earst impressed in her gentle spright:"}, {"location": "Book 3, Cant. IIII., 54.1", "line_text": "But gentle Sleepe enuyde him any rest;"}, {"location": "Book 3, Cant. V., 4.5", "line_text": "Serued a gentle Lady of great sway,"}, {"location": "Book 3, Cant. V., 18.2", "line_text": "The gentle Squire came ryding that same way,"}, {"location": "Book 3, Cant. V., 36.1", "line_text": "Thereat she blushing said, Ah gentle Squire,"}, {"location": "Book 3, Cant. V., 39.9", "line_text": "With gentle murmure, that his course they did restraine."}, {"location": "Book 3, Cant. V., 52.7", "line_text": "In gentle Ladies brest, and bounteous race"}, {"location": "Book 3, Cant. VI., 1.9", "line_text": "And gentle sprite deforme with rude rusticity."}, {"location": "Book 3, Cant. VI., 7.3", "line_text": "To sleepe, the whiles a gentle slombring swowne"}, {"location": "Book 3, Cant. VI., 15.6", "line_text": "And eke the gentle shepheard swaynes, which sat"}, {"location": "Book 3, Cant. VI., 22.9", "line_text": "Spare, gentle sister, with reproch my paine to eeke."}, {"location": "Book 3, Cant. VI., 25.4", "line_text": "With sugred words and gentle blandishment,"}, {"location": "Book 3, Cant. VI., 41.5", "line_text": "And sweet loue gentle fits emongst them throwes,"}, {"location": "Book 3, Cant. VII., 15.4", "line_text": "Her gentle speach applide, that in short space"}, {"location": "Book 3, Cant. VII., 53.6", "line_text": "That gentle Lady, whom I loue and serue,"}, {"location": "Book 3, Cant. VII., 54.6", "line_text": "I might do seruice vnto gentle Dames,"}, {"location": "Book 3, Cant. VII., 56.8", "line_text": "Ah gentle Squire (quoth he) tell at one word,"}, {"location": "Book 3, Cant. VIII., 1.4", "line_text": "This gentle Damzell, whom I wrote vpon,"}, {"location": "Book 3, Cant. VIII., 10.6", "line_text": "Yet still with gentle countenaunce retained,"}, {"location": "Book 3, Cant. VIII., 11.4", "line_text": "In th'open freshnesse of the gentle aire,"}, {"location": "Book 3, Cant. VIII., 14.2", "line_text": "He gan make gentle purpose to his Dame,"}, {"location": "Book 3, Cant. VIII., 35.9", "line_text": "And there with many gentle termes her faire besought."}, {"location": "Book 3, Cant. VIII., 47.1", "line_text": "Ah gentle knight (said then Sir Satyrane)"}, {"location": "Book 3, Cant. IX., 7.7", "line_text": "But fast good will with gentle curtesyes,"}, {"location": "Book 3, Cant. IX., 9.2", "line_text": "The man by gentle meanes, to let vs in,"}, {"location": "Book 3, Cant. IX., 26.9", "line_text": "And shewd her selfe in all a gentle curteous Dame."}, {"location": "Book 3, Cant. IX., 32.2", "line_text": "Purpose was moued by that gentle Dame,"}, {"location": "Book 3, Cant. X., 36.1", "line_text": "The gentle Lady, loose at randon left,"}, {"location": "Book 3, Cant. XI., 14.1", "line_text": "Ah gentle knight, whose deepe conceiued griefe"}, {"location": "Book 3, Cant. XI., 15.3", "line_text": "Hath outrag'd you, and thrald your gentle make."}, {"location": "Book 3, Cant. XI., 18.6", "line_text": "As gentle Ladies helplesse misery."}, {"location": "Book 3, Cant. XI., 44.2", "line_text": "And gentle pangues, with which he maked meeke"}, {"location": "Book 3, Cant. XII., 14.3", "line_text": "For she was gentle, and of milde aspect,"}, {"location": "Book 3, Cant. XII., 40.2", "line_text": "Said, Gentle Dame, reward enough I weene"}, {"location": "Book 3, Cant. XII., 40.9", "line_text": "Hath no lesse griefe endured for your gentle sake."}, {"location": "Book 3, Cant. XII., 44.6", "line_text": "But most faire Amoret, whose gentle spright"}, {"location": "Book 3, Cant. XII., 50.7", "line_text": "Was much empassiond in her gentle sprite,"}, {"location": "Book 4, Canto I., 15.1", "line_text": "But that young Knight, which through her gentle deed"}, {"location": "Book 4, Canto I., 46.1", "line_text": "Ah gentle knight then false Duessa sayd,"}, {"location": "Book 4, Canto I., 46.4", "line_text": "Mongst gentle Knights to nourish euermore?"}, {"location": "Book 4, Cant. II., 22.3", "line_text": "Ah gentle knights (quoth he) how may that bee,"}, {"location": "Book 4, Cant. II., 30.7", "line_text": "That twixt themselues did gentle purpose make"}, {"location": "Book 4, Cant. III., 50.1", "line_text": "All which, when gentle Canacee beheld,"}, {"location": "Book 4, Cant. IIII., 48.7", "line_text": "To ioyous feast and other gentle play;"}, {"location": "Book 4, Cant. V., 19.2", "line_text": "Till that at last the gentle Amoret"}, {"location": "Book 4, Cant. V., 30.7", "line_text": "The gentle Scudamour, whose hart whileare"}, {"location": "Book 4, Cant. V., 40.2", "line_text": "When gentle sleepe his heauie eyes would close;"}, {"location": "Book 4, Cant. VI., 1.2", "line_text": "And pyning anguish hid in gentle hart,"}, {"location": "Book 4, Cant. VI., 3.7", "line_text": "Ah gentle Scudamour, vnto your grace"}, {"location": "Book 4, Cant. VI., 30.2", "line_text": "Ye gentle Knights, whom fortune here hath brought,"}, {"location": "Book 4, Cant. VI., 40.4", "line_text": "Continuall siege vnto her gentle hart;"}, {"location": "Book 4, Cant. VII., 2.4", "line_text": "The louely Amoret, whose gentle hart"}, {"location": "Book 4, Cant. VII., 15.6", "line_text": "It was my lot to loue a gentle swaine,"}, {"location": "Book 4, Cant. VII., 24.3", "line_text": "And that same gentle Squire arriu'd in place,"}, {"location": "Book 4, Cant. VII., 25.1", "line_text": "Which drery sight the gentle Squire espying,"}, {"location": "Book 4, Cant. VII., 35.2", "line_text": "She left the gentle Squire with Amoret:"}, {"location": "Book 4, Cant. VII., 45.6", "line_text": "That he whilome some gentle swaine had beene,"}, {"location": "Book 4, Cant. VIII., argument.1", "line_text": "The gentle Squire recouers grace,"}, {"location": "Book 4, Cant. VIII., 1.2", "line_text": "Which to this gentle Squire did happen late."}, {"location": "Book 4, Cant. VIII., 5.1", "line_text": "Thus long this gentle bird to him did vse,"}, {"location": "Book 4, Cant. VIII., 9.9", "line_text": "Her gentle Squire through her displeasure did pertake."}, {"location": "Book 4, Cant. VIII., 22.7", "line_text": "No seruice lothsome to a gentle kind;"}, {"location": "Book 4, Cant. VIII., 29.4", "line_text": "These gentle Ladies will misdeeme too light,"}, {"location": "Book 4, Cant. VIII., 34.3", "line_text": "This gentle crew gan from their eye-lids chace"}, {"location": "Book 4, Cant. VIII., 50.1", "line_text": "So as it fell there was a gentle Squire,"}, {"location": "Book 4, Cant. IX., 1.9", "line_text": "Me seemes the gentle hart should most assured bind."}, {"location": "Book 4, Cant. IX., 4.2", "line_text": "To yeeld strong succour to that gentle swayne,"}, {"location": "Book 4, Cant. IX., 22.2", "line_text": "Were Britomart, and gentle Scudamour,"}, {"location": "Book 4, Cant. IX., 32.9", "line_text": "With gentle words perswading them to friendly peace."}, {"location": "Book 4, Cant. IX., 38.5", "line_text": "Aye me to see that gentle maide so tost."}, {"location": "Book 4, Cant. IX., 40.4", "line_text": "Mote we entreat you, sith this gentle crew"}, {"location": "Book 4, Cant. X., 3.6", "line_text": "Then hearke ye gentle knights and Ladies free,"}, {"location": "Book 4, Cant. X., 24.4", "line_text": "Soft rombling brookes, that gentle slomber drew;"}, {"location": "Book 4, Cant. X., 36.2", "line_text": "But she in gentle wise me entertayned,"}, {"location": "Book 4, Cant. X., 51.2", "line_text": "Holding her hand vpon her gentle hart;"}, {"location": "Book 4, Cant. XI., 34.9", "line_text": "With many a gentle Muse, and many a learned wit."}, {"location": "Book 4, Cant. XI., 43.1", "line_text": "The first, the gentle Shure that making way"}, {"location": "Book 5, Canto I., 1.5", "line_text": "And with their boughes the gentle plants did beat."}, {"location": "Book 5, Canto I., 6.2", "line_text": "Vpon a day she found this gentle childe,"}, {"location": "Book 5, Cant. III., 16.8", "line_text": "Much did his words the gentle Ladie quell,"}, {"location": "Book 5, Cant. V., 15.2", "line_text": "A gentle Faulcon sitting on an hill,"}, {"location": "Book 5, Cant. V., 15.6", "line_text": "Doth beat vpon the gentle bird in vaine,"}, {"location": "Book 5, Cant. VI., 2.2", "line_text": "This gentle knight himselfe so well behaued,"}, {"location": "Book 5, Cant. VIII., 11.2", "line_text": "Ah gentle Knights, what meane ye thus vnwise"}, {"location": "Book 5, Cant. IX., 20.1", "line_text": "Thence forth they passed with that gentle Mayd,"}, {"location": "Book 5, Cant. IX., 21.1", "line_text": "The gentle knights reioyced much to heare"}, {"location": "Book 5, Cant. X., 17.6", "line_text": "With those two gentle youthes, which him did guide,"}, {"location": "Book 5, Cant. XI., 64.1", "line_text": "Much was the Ladie in her gentle mind"}, {"location": "Book 6, Canto I., 26.8", "line_text": "Both noble armes and gentle curtesie."}, {"location": "Book 6, Cant. II., 6.3", "line_text": "As then the guize was for each gentle swayne;"}, {"location": "Book 6, Cant. II., 7.2", "line_text": "At length bespake; What meanes this, gentle swaine?"}, {"location": "Book 6, Cant. II., 8.8", "line_text": "But then aread, thou gentle chyld, wherefore"}, {"location": "Book 6, Cant. II., 24.1", "line_text": "Then turning backe vnto that gentle boy,"}, {"location": "Book 6, Cant. II., 25.1", "line_text": "Faire gentle swayne, and yet as stout as fayre,"}, {"location": "Book 6, Cant. II., 31.5", "line_text": "In gentle thewes, and such like seemely leres."}, {"location": "Book 6, Cant. II., 46.2", "line_text": "Which ye haue gathered to your gentle hart,"}, {"location": "Book 6, Cant. III., 1.2", "line_text": "The gentle minde by gentle deeds is knowne."}, {"location": "Book 6, Cant. III., 1.2", "line_text": "The gentle minde by gentle deeds is knowne."}, {"location": "Book 6, Cant. III., 2.2", "line_text": "That gentle bloud will gentle manners breed;"}, {"location": "Book 6, Cant. III., 2.2", "line_text": "That gentle bloud will gentle manners breed;"}, {"location": "Book 6, Cant. III., 8.4", "line_text": "The gentle Aladine did earst inuade,"}, {"location": "Book 6, Cant. III., 22.1", "line_text": "With which his gentle words and goodly wit"}, {"location": "Book 6, Cant. III., 23.3", "line_text": "Allur'd with myldnesse of the gentle wether,"}, {"location": "Book 6, Cant. IIII., 2.8", "line_text": "Chasing the gentle Calepine around,"}, {"location": "Book 6, Cant. V., 1.2", "line_text": "The gentle bloud, how euer it be wrapt"}, {"location": "Book 6, Cant. V., 1.8", "line_text": "Yet will it shew some sparkes of gentle mynd,"}, {"location": "Book 6, Cant. V., 2.5", "line_text": "Yet shewd some token of his gentle blood,"}, {"location": "Book 6, Cant. V., 2.6", "line_text": "By gentle vsage of that wretched Dame."}, {"location": "Book 6, Cant. V., 29.9", "line_text": "So milde humanity, and perfect gentle mynd."}, {"location": "Book 6, Cant. V., 36.7", "line_text": "Some goodly person, and of gentle race,"}, {"location": "Book 6, Cant. V., 39.7", "line_text": "Ne yet that gentle Squire, for grieuous paine"}, {"location": "Book 6, Cant. VII., 1.1", "line_text": "Like as the gentle hart it selfe bewrayes,"}, {"location": "Book 6, Cant. VII., 1.2", "line_text": "In doing gentle deedes with franke delight,"}, {"location": "Book 6, Cant. VII., 6.7", "line_text": "The gentle Prince not farre away they spyde,"}, {"location": "Book 6, Cant. VII., 23.1", "line_text": "Nathelesse for all his speach, the gentle knight"}, {"location": "Book 6, Cant. VII., 28.9", "line_text": "In th'harts of many a knight, and many a gentle squire."}, {"location": "Book 6, Cant. VII., 39.2", "line_text": "When as the gentle Squire, with faire Serene,"}, {"location": "Book 6, Cant. VII., 45.3", "line_text": "His gentle heart with indignation sweld,"}, {"location": "Book 6, Cant. VII., 49.7", "line_text": "He would him scorne, that to his gentle mynd"}, {"location": "Book 6, Cant. VIII., 1.1", "line_text": "Y e gentle Ladies, in whose soueraine powre"}, {"location": "Book 6, Cant. VIII., 3.1", "line_text": "Who after thraldome of the gentle Squire,"}, {"location": "Book 6, Cant. VIII., 20.5", "line_text": "I was belou'd of many a gentle Knight,"}, {"location": "Book 6, Cant. VIII., 27.6", "line_text": "It was his owne true groome, the gentle Squire,"}, {"location": "Book 6, Cant. VIII., 31.3", "line_text": "When first the gentle Squire at variaunce fell"}, {"location": "Book 6, Cant. IX., 2.1", "line_text": "Great trauell hath the gentle Calidore"}, {"location": "Book 6, Cant. IX., 7.2", "line_text": "And tooke their gentle offer: so adowne"}, {"location": "Book 6, Cant. IX., 18.3", "line_text": "The gentle knight, as he that did excell"}, {"location": "Book 6, Cant. IX., 45.1", "line_text": "Thus did the gentle knight himselfe abeare"}, {"location": "Book 6, Cant. X., 7.1", "line_text": "And at the foote thereof, a gentle flud"}], "split_num": 0}]